activepy/__init__.py
activepy/activepy.py
activepy/cli.py
activepy-1.0.7.dist-info/METADATA
activepy-1.0.7.dist-info/WHEEL
activepy-1.0.7.dist-info/entry_points.txt
activepy-1.0.7.dist-info/top_level.txt
activepy-1.0.7.dist-info/RECORD
