Metadata-Version: 2.2
Name: activepy
Version: 1.0.7
Summary: A command-line utility for creating and managing Python webapp applications.
Author: Simone
Author-email: cardellasimone10@gmail.com
Classifier: Programming Language :: Python :: 3
Classifier: License :: OSI Approved :: MIT License
Classifier: Operating System :: OS Independent
Requires-Python: >=3.6
Requires-Dist: colorama
Dynamic: author
Dynamic: author-email
Dynamic: classifier
Dynamic: description
Dynamic: description-content-type
Dynamic: requires-dist
Dynamic: requires-python
Dynamic: summary
